sds_toolbox/__init__.py
sds_toolbox/common.py
sds_toolbox/db.py
sds_toolbox/queries.py
sds_toolbox/sds.py
sds_toolbox/settings.py
sds_toolbox-0.0.7.dist-info/METADATA
sds_toolbox-0.0.7.dist-info/WHEEL
sds_toolbox-0.0.7.dist-info/top_level.txt
sds_toolbox-0.0.7.dist-info/RECORD
