Metadata-Version: 2.1
Name: sds-toolbox
Version: 0.0.7
Summary: A complete toolbox to interact with the SDS
Home-page: UNKNOWN
Author: Erwan Le Nagard
Author-email: erwan@opsci.ai
License: MIT
Platform: UNKNOWN
Requires-Dist: sqlalchemy
Requires-Dist: pydantic
Requires-Dist: pydantic-settings
Requires-Dist: pandas
Requires-Dist: humanize
